resarchpaper/__init__.py
resarchpaper/__main__.py
resarchpaper/cli.py
resarchpaper/csvwriter.py
resarchpaper/pubmed_fetcher.py
resarchpaper/pubmed_processing.py
resarchpaper-0.1.0.dist-info/entry_points.txt
resarchpaper-0.1.0.dist-info/METADATA
resarchpaper-0.1.0.dist-info/WHEEL
resarchpaper-0.1.0.dist-info/RECORD
