Metadata-Version: 2.3
Name: resarchpaper
Version: 0.1.0
Summary: CLI tool to fetch PubMed papers with non-academic authors
Author: Rituja DIkshit
Author-email: dikshitrituja@gmail.com
Requires-Python: >=3.8,<4.0
Classifier: Programming Language :: Python :: 3
Classifier: Programming Language :: Python :: 3.8
Classifier: Programming Language :: Python :: 3.9
Classifier: Programming Language :: Python :: 3.10
Classifier: Programming Language :: Python :: 3.11
Classifier: Programming Language :: Python :: 3.12
Classifier: Programming Language :: Python :: 3.13
Requires-Dist: biopython (>=1.81,<2.0)
Requires-Dist: typer[all] (>=0.12.3,<0.13.0)
